taskwarrior_syncall/__init__.py
taskwarrior_syncall/aggregator.py
taskwarrior_syncall/app_utils.py
taskwarrior_syncall/asana/__init__.py
taskwarrior_syncall/asana/asana_side.py
taskwarrior_syncall/asana/asana_task.py
taskwarrior_syncall/asana/utils.py
taskwarrior_syncall/cli.py
taskwarrior_syncall/constants.py
taskwarrior_syncall/google/__init__.py
taskwarrior_syncall/google/gcal_side.py
taskwarrior_syncall/google/gkeep_todo_item.py
taskwarrior_syncall/google/gkeep_todo_side.py
taskwarrior_syncall/google/google_side.py
taskwarrior_syncall/notion_side.py
taskwarrior_syncall/notion_todo_block.py
taskwarrior_syncall/res/gcal_client_secret.json
taskwarrior_syncall/scripts/tw_asana_sync.py
taskwarrior_syncall/scripts/tw_gcal_sync.py
taskwarrior_syncall/scripts/tw_gkeep_sync.py
taskwarrior_syncall/scripts/tw_notion_sync.py
taskwarrior_syncall/side_helper.py
taskwarrior_syncall/sync_side.py
taskwarrior_syncall/taskwarrior_side.py
taskwarrior_syncall/tw_asana_utils.py
taskwarrior_syncall/tw_gcal_utils.py
taskwarrior_syncall/tw_gkeep_utils.py
taskwarrior_syncall/tw_notion_utils.py
taskwarrior_syncall/types.py
taskwarrior_syncall-1.3.3.dist-info/WHEEL
taskwarrior_syncall-1.3.3.dist-info/LICENSE
taskwarrior_syncall-1.3.3.dist-info/METADATA
taskwarrior_syncall-1.3.3.dist-info/RECORD
