Metadata-Version: 2.1
Name: taskwarrior-syncall
Version: 1.3.3
Summary: Taskwarrior <-> * bi-directional synchronization tool - this is now deprecated, use syncall instead
Home-page: https://github.com/bergercookie/taskwarrior_syncall
License: MIT
Keywords: asana,calendar,gkeep,google calendar,google keep,google,notion,productivity,synchronization,task management,taskwarrior
Author: Nikos Koukis
Author-email: nickkouk@gmail.com
Requires-Python: >=3.8,<4.0
Classifier: Environment :: Console
Classifier: Framework :: Pytest
Classifier: Intended Audience :: End Users/Desktop
Classifier: License :: OSI Approved :: MIT License
Classifier: Natural Language :: English
Classifier: Operating System :: Unix
Classifier: Programming Language :: Python
Classifier: Programming Language :: Python :: 3
Classifier: Programming Language :: Python :: 3.8
Classifier: Programming Language :: Python :: 3.9
Classifier: Programming Language :: Python :: 3.10
Classifier: Programming Language :: Python :: 3.11
Classifier: Programming Language :: Python :: 3
Classifier: Programming Language :: Python :: 3 :: Only
Classifier: Programming Language :: Python :: 3.10
Classifier: Programming Language :: Python :: 3.8
Classifier: Programming Language :: Python :: 3.9
Classifier: Topic :: Utilities
Requires-Dist: syncall[google,notion,gkeep,asana,tw] (>=1.4.0,<2.0.0)
Project-URL: Repository, https://github.com/bergercookie/taskwarrior_syncall
